encolor/__init__.py
encolor/__main__.py
encolor/gfx.py
encolor/sub.py
encolor/utils.py
encolor-0.1.0.dist-info/LICENSE
encolor-0.1.0.dist-info/METADATA
encolor-0.1.0.dist-info/WHEEL
encolor-0.1.0.dist-info/entry_points.txt
encolor-0.1.0.dist-info/top_level.txt
encolor-0.1.0.dist-info/RECORD
