Metadata-Version: 2.1
Name: encolor
Version: 0.1.0
Summary: Easily automate colorizing terminal output
Author-email: Froloket64 <gh@froloket.anonaddy.com>
Project-URL: Homepage, https://github.com/Froloket64/encolor
Project-URL: Bug Tracker, https://github.com/Froloket64/encolor/issues
Classifier: Programming Language :: Python :: 3
Classifier: License :: OSI Approved :: GNU General Public License v3 (GPLv3)
Classifier: Operating System :: Unix
Requires-Python: >=3.7
License-File: LICENSE
